setup.cfg
setup.py
dotbrain_module/__init__.py
dotbrain_module/functions.py
dotbrain_module.egg-info/PKG-INFO
dotbrain_module.egg-info/SOURCES.txt
dotbrain_module.egg-info/dependency_links.txt
dotbrain_module.egg-info/top_level.txt