Metadata-Version: 1.1
Name: dotbrain-module
Version: 0.3.1
Summary: V 0.3.1 dotBrain Module
Home-page: https://github.com/luisda199824/dotbrain_module
Author: Luis David Ocampo Aguirre
Author-email: luisda199824@gmail.com
License: UNKNOWN
Download-URL: https://github.com/luisda199824/dotbrain_module/archive/0.3.1.tar.gz
Keywords: testing,dotbrain,private
Platform: UNKNOWN
